LICENSE.txt
MANIFEST.in
setup.cfg
setup.py
businessdatetime/__init__.py
python_business_datetime.egg-info/PKG-INFO
python_business_datetime.egg-info/SOURCES.txt
python_business_datetime.egg-info/dependency_links.txt
python_business_datetime.egg-info/not-zip-safe
python_business_datetime.egg-info/top_level.txt