Metadata-Version: 1.1
Name: python-business-datetime
Version: 0.0.1
Summary: A simple way to calculate working hours between two dates
Home-page: http://github.com/ziplokk/BusinessDatetime
Author: Mark Sanders
Author-email: sdscdeveloper@gmail.com
License: LICENSE.txt
Platform: OS Independent
Classifier: Development Status :: 2 - Pre-Alpha
Classifier: Environment :: Web Environment
Classifier: Intended Audience :: Developers
Classifier: License :: OSI Approved :: BSD License
Classifier: Operating System :: OS Independent
Classifier: Programming Language :: Python
Classifier: Topic :: Internet :: WWW/HTTP :: Dynamic Content
Classifier: Topic :: Software Development
Classifier: Topic :: Software Development :: Libraries :: Application Frameworks
Classifier: Programming Language :: Python :: 2
Classifier: Programming Language :: Python :: 2.6
Classifier: Programming Language :: Python :: 2.7
